iflow_mcp_mcp_server_python-0.1.1.dist-info/licenses/LICENSE
inkeep_mcp_server/__init__.py
inkeep_mcp_server/__main__.py
inkeep_mcp_server/app.py
inkeep_mcp_server/server.py
inkeep_mcp_server/settings.py
iflow_mcp_mcp_server_python-0.1.1.dist-info/METADATA
iflow_mcp_mcp_server_python-0.1.1.dist-info/WHEEL
iflow_mcp_mcp_server_python-0.1.1.dist-info/entry_points.txt
iflow_mcp_mcp_server_python-0.1.1.dist-info/top_level.txt
iflow_mcp_mcp_server_python-0.1.1.dist-info/RECORD
