Metadata-Version: 2.4
Name: iflow-mcp_mcp-server-python
Version: 0.1.1
Summary: Inkeep MCP Server
Requires-Python: >=3.10
License-File: LICENSE
Requires-Dist: fastapi[standard]>=0.115.12
Requires-Dist: mcp[cli]>=1.3.0
Requires-Dist: openai>=1.66.3
Requires-Dist: pydantic-settings>=2.8.1
Dynamic: license-file
